owl_server/__init__.py
owl_server/cli.py
owl_server/config.py
owl_server/crypto.py
owl_server/database.py
owl_server/k8s.py
owl_server/log.py
owl_server/plugins.py
owl_server/schema.py
owl_server/utils.py
owl_server/api/__init__.py
owl_server/daemon/__init__.py
owl_server/daemon/pipeline.py
owl_server/daemon/scheduler.py
owl_server/daemon/utils.py
owl_server/migrations/__init__.py
owl_server/migrations/env.py
owl_server/migrations/migrate.py
owl_server/migrations/versions/20210804_initial_revision.py
owl_server/migrations/versions/__init__.py
owl_server/pipelines/__init__.py
owl_server/scripts/__init__.py
owl_server/scripts/run_api.py
owl_server/scripts/run_pipeline.py
owl_server/scripts/run_scheduler.py
owl_pipeline_server-0.8.3.dist-info/AUTHORS.rst
owl_pipeline_server-0.8.3.dist-info/LICENSE
owl_pipeline_server-0.8.3.dist-info/METADATA
owl_pipeline_server-0.8.3.dist-info/WHEEL
owl_pipeline_server-0.8.3.dist-info/entry_points.txt
owl_pipeline_server-0.8.3.dist-info/top_level.txt
owl_pipeline_server-0.8.3.dist-info/RECORD
